[
    {
        "id": 1007669261261778944,
        "name": "Mgibbs0325",
        "screen_name": "mgibbs0325",
        "location": "Salem, MO"
    },
    {
        "id": 399361313,
        "name": "Steve Holroyd #FBPE",
        "screen_name": "HolroydSteve",
        "location": "Cumbria"
    },
    {
        "id": 952300568961220609,
        "name": "Project Hope",
        "screen_name": "ProjectHope56",
        "location": "London"
    },
    {
        "id": 3065599859,
        "name": "Alan Fraser",
        "screen_name": "CanonImages15",
        "location": "South East, England"
    },
    {
        "id": 101070604,
        "name": "P.S. This ROCKS by Christi Tasker",
        "screen_name": "PSthisRocks",
        "location": "150 SE 25th Road, #4D Miami, FL 33129"
    },
    {
        "id": 3275071813,
        "name": "Bri Sullivan | Houston Newborn Photography",
        "screen_name": "babypicts",
        "location": "Houston, TX"
    },
    {
        "id": 880497679326998530,
        "name": "janett dejarnette",
        "screen_name": "dejadivasphotos",
        "location": "Salem, MA"
    },
    {
        "id": 4165329244,
        "name": "Art with soul",
        "screen_name": "ArtWithSoul2311",
        "location": "Spain"
    },
    {
        "id": 866238336,
        "name": "Andreas Marantika",
        "screen_name": "andre_marantika",
        "location": "Indonesia"
    },
    {
        "id": 59490048,
        "name": "Julia",
        "screen_name": "LondonInPhotos",
        "location": "London"
    }
]